topsis/__init__.py
topsis/cli.py
topsis_vedika_102313060-1.0.0.dist-info/METADATA
topsis_vedika_102313060-1.0.0.dist-info/WHEEL
topsis_vedika_102313060-1.0.0.dist-info/entry_points.txt
topsis_vedika_102313060-1.0.0.dist-info/top_level.txt
topsis_vedika_102313060-1.0.0.dist-info/RECORD
