Metadata-Version: 2.4
Name: Topsis-Vedika-102313060
Version: 1.0.0
Requires-Dist: pandas
Requires-Dist: numpy
Dynamic: description
Dynamic: description-content-type
Dynamic: requires-dist
